{"box_data": [{"position": {"minX": 38.625, "minY": 195.0, "maxX": 309.0, "maxY": 414.0}, "class_id": 1, "box_caption": "rifle 0.007", "scores": {"class_score": 0.007228851318359375}, "domain": "pixel"}, {"position": {"minX": 38.625, "minY": 195.0, "maxX": 309.0, "maxY": 414.0}, "class_id": 0, "box_caption": "gun 0.007", "scores": {"class_score": 0.00661468505859375}, "domain": "pixel"}, {"position": {"minX": 15.125, "minY": 259.0, "maxX": 271.0, "maxY": 415.5}, "class_id": 1, "box_caption": "rifle 0.006", "scores": {"class_score": 0.006443023681640625}, "domain": "pixel"}, {"position": {"minX": 8.25, "minY": 323.75, "maxX": 279.25, "maxY": 413.75}, "class_id": 1, "box_caption": "rifle 0.006", "scores": {"class_score": 0.0058746337890625}, "domain": "pixel"}, {"position": {"minX": 15.125, "minY": 259.0, "maxX": 271.0, "maxY": 415.5}, "class_id": 0, "box_caption": "gun 0.006", "scores": {"class_score": 0.005687713623046875}, "domain": "pixel"}, {"position": {"minX": 38.625, "minY": 195.0, "maxX": 309.0, "maxY": 414.0}, "class_id": 2, "box_caption": "knife 0.005", "scores": {"class_score": 0.00507354736328125}, "domain": "pixel"}, {"position": {"minX": 8.25, "minY": 323.75, "maxX": 279.25, "maxY": 413.75}, "class_id": 0, "box_caption": "gun 0.005", "scores": {"class_score": 0.004688262939453125}, "domain": "pixel"}, {"position": {"minX": 78.5, "minY": 253.125, "maxX": 331.25, "maxY": 416.5}, "class_id": 1, "box_caption": "rifle 0.004", "scores": {"class_score": 0.00433349609375}, "domain": "pixel"}, {"position": {"minX": 420.5, "minY": -1.125, "maxX": 701.5, "maxY": 286.0}, "class_id": 2, "box_caption": "knife 0.004", "scores": {"class_score": 0.00417327880859375}, "domain": "pixel"}, {"position": {"minX": 15.125, "minY": 259.0, "maxX": 271.0, "maxY": 415.5}, "class_id": 2, "box_caption": "knife 0.004", "scores": {"class_score": 0.004093170166015625}, "domain": "pixel"}, {"position": {"minX": 437.25, "minY": 75.0, "maxX": 685.0, "maxY": 410.75}, "class_id": 2, "box_caption": "knife 0.004", "scores": {"class_score": 0.0040130615234375}, "domain": "pixel"}, {"position": {"minX": 224.125, "minY": 88.375, "maxX": 642.0, "maxY": 397.5}, "class_id": 2, "box_caption": "knife 0.004", "scores": {"class_score": 0.00392913818359375}, "domain": "pixel"}, {"position": {"minX": 9.875, "minY": 196.875, "maxX": 215.875, "maxY": 413.0}, "class_id": 1, "box_caption": "rifle 0.004", "scores": {"class_score": 0.003917694091796875}, "domain": "pixel"}, {"position": {"minX": 134.125, "minY": 9.5, "maxX": 478.0, "maxY": 272.75}, "class_id": 2, "box_caption": "knife 0.004", "scores": {"class_score": 0.0038585662841796875}, "domain": "pixel"}, {"position": {"minX": 6.25, "minY": -2.0, "maxX": 278.5, "maxY": 283.0}, "class_id": 2, "box_caption": "knife 0.004", "scores": {"class_score": 0.003818511962890625}, "domain": "pixel"}, {"position": {"minX": 183.0, "minY": 10.875, "maxX": 490.0, "maxY": 272.0}, "class_id": 1, "box_caption": "rifle 0.004", "scores": {"class_score": 0.003795623779296875}, "domain": "pixel"}, {"position": {"minX": 3.8125, "minY": 195.75, "maxX": 220.5, "maxY": 414.25}, "class_id": 2, "box_caption": "knife 0.004", "scores": {"class_score": 0.0036602020263671875}, "domain": "pixel"}, {"position": {"minX": 183.0, "minY": 10.875, "maxX": 490.0, "maxY": 272.0}, "class_id": 0, "box_caption": "gun 0.004", "scores": {"class_score": 0.0036449432373046875}, "domain": "pixel"}, {"position": {"minX": 226.375, "minY": 12.5, "maxX": 637.5, "maxY": 275.75}, "class_id": 2, "box_caption": "knife 0.004", "scores": {"class_score": 0.0035610198974609375}, "domain": "pixel"}, {"position": {"minX": 207.25, "minY": 3.125, "maxX": 463.25, "maxY": 218.0}, "class_id": 2, "box_caption": "knife 0.004", "scores": {"class_score": 0.0035266876220703125}, "domain": "pixel"}, {"position": {"minX": 3.8125, "minY": 195.75, "maxX": 220.5, "maxY": 414.25}, "class_id": 0, "box_caption": "gun 0.003", "scores": {"class_score": 0.0034885406494140625}, "domain": "pixel"}, {"position": {"minX": 61.0, "minY": 147.625, "maxX": 481.0, "maxY": 404.0}, "class_id": 2, "box_caption": "knife 0.003", "scores": {"class_score": 0.00335693359375}, "domain": "pixel"}, {"position": {"minX": 8.25, "minY": 323.75, "maxX": 279.25, "maxY": 413.75}, "class_id": 2, "box_caption": "knife 0.003", "scores": {"class_score": 0.0033359527587890625}, "domain": "pixel"}, {"position": {"minX": 4.0625, "minY": -1.4375, "maxX": 214.75, "maxY": 222.75}, "class_id": 2, "box_caption": "knife 0.003", "scores": {"class_score": 0.0033321380615234375}, "domain": "pixel"}, {"position": {"minX": 45.375, "minY": 4.3125, "maxX": 438.5, "maxY": 220.75}, "class_id": 2, "box_caption": "knife 0.003", "scores": {"class_score": 0.0033321380615234375}, "domain": "pixel"}, {"position": {"minX": -5.625, "minY": -2.375, "maxX": 354.5, "maxY": 163.375}, "class_id": 2, "box_caption": "knife 0.003", "scores": {"class_score": 0.00331878662109375}, "domain": "pixel"}, {"position": {"minX": 199.5, "minY": 82.125, "maxX": 662.0, "maxY": 399.0}, "class_id": 0, "box_caption": "gun 0.003", "scores": {"class_score": 0.003307342529296875}, "domain": "pixel"}, {"position": {"minX": 442.0, "minY": -2.3125, "maxX": 680.0, "maxY": 161.0}, "class_id": 2, "box_caption": "knife 0.003", "scores": {"class_score": 0.00328826904296875}, "domain": "pixel"}, {"position": {"minX": 188.75, "minY": 4.0, "maxX": 421.25, "maxY": 151.75}, "class_id": 1, "box_caption": "rifle 0.003", "scores": {"class_score": 0.003253936767578125}, "domain": "pixel"}, {"position": {"minX": 33.375, "minY": 309.5, "maxX": 380.5, "maxY": 415.5}, "class_id": 1, "box_caption": "rifle 0.003", "scores": {"class_score": 0.0031528472900390625}, "domain": "pixel"}, {"position": {"minX": 486.5, "minY": -6.9375, "maxX": 693.5, "maxY": 229.25}, "class_id": 2, "box_caption": "knife 0.003", "scores": {"class_score": 0.0031490325927734375}, "domain": "pixel"}, {"position": {"minX": 2.125, "minY": -4.0, "maxX": 158.625, "maxY": 161.0}, "class_id": 2, "box_caption": "knife 0.003", "scores": {"class_score": 0.003101348876953125}, "domain": "pixel"}, {"position": {"minX": 199.5, "minY": 82.125, "maxX": 662.0, "maxY": 399.0}, "class_id": 1, "box_caption": "rifle 0.003", "scores": {"class_score": 0.0030975341796875}, "domain": "pixel"}, {"position": {"minX": 57.625, "minY": 149.875, "maxX": 417.0, "maxY": 398.5}, "class_id": 1, "box_caption": "rifle 0.003", "scores": {"class_score": 0.003086090087890625}, "domain": "pixel"}, {"position": {"minX": 188.75, "minY": 4.0, "maxX": 421.25, "maxY": 151.75}, "class_id": 2, "box_caption": "knife 0.003", "scores": {"class_score": 0.00307464599609375}, "domain": "pixel"}, {"position": {"minX": 78.5, "minY": 253.125, "maxX": 331.25, "maxY": 416.5}, "class_id": 0, "box_caption": "gun 0.003", "scores": {"class_score": 0.0029621124267578125}, "domain": "pixel"}, {"position": {"minX": 8.375, "minY": 256.5, "maxX": 155.125, "maxY": 415.5}, "class_id": 1, "box_caption": "rifle 0.003", "scores": {"class_score": 0.0029239654541015625}, "domain": "pixel"}, {"position": {"minX": 96.0, "minY": 4.75, "maxX": 452.5, "maxY": 217.5}, "class_id": 1, "box_caption": "rifle 0.003", "scores": {"class_score": 0.0029144287109375}, "domain": "pixel"}, {"position": {"minX": 437.25, "minY": 75.0, "maxX": 685.0, "maxY": 410.75}, "class_id": 0, "box_caption": "gun 0.003", "scores": {"class_score": 0.002899169921875}, "domain": "pixel"}, {"position": {"minX": 10.0, "minY": 94.375, "maxX": 279.5, "maxY": 391.0}, "class_id": 2, "box_caption": "knife 0.003", "scores": {"class_score": 0.002895355224609375}, "domain": "pixel"}, {"position": {"minX": 31.5, "minY": 89.25, "maxX": 319.0, "maxY": 395.75}, "class_id": 1, "box_caption": "rifle 0.003", "scores": {"class_score": 0.0028858184814453125}, "domain": "pixel"}, {"position": {"minX": 328.0, "minY": 0.375, "maxX": 665.0, "maxY": 222.75}, "class_id": 2, "box_caption": "knife 0.003", "scores": {"class_score": 0.0028705596923828125}, "domain": "pixel"}, {"position": {"minX": 420.5, "minY": -1.125, "maxX": 701.5, "maxY": 286.0}, "class_id": 0, "box_caption": "gun 0.003", "scores": {"class_score": 0.002838134765625}, "domain": "pixel"}, {"position": {"minX": 66.625, "minY": 263.0, "maxX": 405.5, "maxY": 414.0}, "class_id": 2, "box_caption": "knife 0.003", "scores": {"class_score": 0.002777099609375}, "domain": "pixel"}, {"position": {"minX": 318.25, "minY": 139.25, "maxX": 673.0, "maxY": 407.75}, "class_id": 2, "box_caption": "knife 0.003", "scores": {"class_score": 0.0027751922607421875}, "domain": "pixel"}, {"position": {"minX": 77.25, "minY": 153.25, "maxX": 397.5, "maxY": 397.25}, "class_id": 0, "box_caption": "gun 0.003", "scores": {"class_score": 0.0027332305908203125}, "domain": "pixel"}, {"position": {"minX": -2.25, "minY": 323.75, "maxX": 162.5, "maxY": 413.75}, "class_id": 1, "box_caption": "rifle 0.003", "scores": {"class_score": 0.0027256011962890625}, "domain": "pixel"}, {"position": {"minX": 7.625, "minY": 2.3125, "maxX": 213.625, "maxY": 156.5}, "class_id": 1, "box_caption": "rifle 0.003", "scores": {"class_score": 0.0026912689208984375}, "domain": "pixel"}, {"position": {"minX": 310.5, "minY": 10.75, "maxX": 681.5, "maxY": 340.0}, "class_id": 2, "box_caption": "knife 0.003", "scores": {"class_score": 0.00266265869140625}, "domain": "pixel"}, {"position": {"minX": 5.375, "minY": 260.75, "maxX": 153.25, "maxY": 414.25}, "class_id": 2, "box_caption": "knife 0.003", "scores": {"class_score": 0.0026607513427734375}, "domain": "pixel"}, {"position": {"minX": 251.5, "minY": 1.8125, "maxX": 479.5, "maxY": 156.0}, "class_id": 2, "box_caption": "knife 0.003", "scores": {"class_score": 0.002651214599609375}, "domain": "pixel"}, {"position": {"minX": 188.75, "minY": 4.0, "maxX": 421.25, "maxY": 151.75}, "class_id": 0, "box_caption": "gun 0.003", "scores": {"class_score": 0.0026187896728515625}, "domain": "pixel"}, {"position": {"minX": 226.375, "minY": 12.5, "maxX": 637.5, "maxY": 275.75}, "class_id": 0, "box_caption": "gun 0.003", "scores": {"class_score": 0.0026149749755859375}, "domain": "pixel"}, {"position": {"minX": 96.0, "minY": 4.75, "maxX": 452.5, "maxY": 217.5}, "class_id": 0, "box_caption": "gun 0.003", "scores": {"class_score": 0.002613067626953125}, "domain": "pixel"}, {"position": {"minX": 418.5, "minY": 1.5, "maxX": 701.5, "maxY": 285.5}, "class_id": 1, "box_caption": "rifle 0.003", "scores": {"class_score": 0.0026092529296875}, "domain": "pixel"}, {"position": {"minX": 31.5, "minY": 89.25, "maxX": 319.0, "maxY": 395.75}, "class_id": 0, "box_caption": "gun 0.003", "scores": {"class_score": 0.0026073455810546875}, "domain": "pixel"}, {"position": {"minX": 6.25, "minY": -2.0, "maxX": 278.5, "maxY": 283.0}, "class_id": 0, "box_caption": "gun 0.003", "scores": {"class_score": 0.0025787353515625}, "domain": "pixel"}, {"position": {"minX": 208.125, "minY": 10.125, "maxX": 654.5, "maxY": 278.5}, "class_id": 1, "box_caption": "rifle 0.003", "scores": {"class_score": 0.002574920654296875}, "domain": "pixel"}, {"position": {"minX": 504.25, "minY": 125.75, "maxX": 677.0, "maxY": 420.75}, "class_id": 2, "box_caption": "knife 0.003", "scores": {"class_score": 0.0025691986083984375}, "domain": "pixel"}, {"position": {"minX": 436.5, "minY": 69.5, "maxX": 681.5, "maxY": 412.75}, "class_id": 1, "box_caption": "rifle 0.003", "scores": {"class_score": 0.00250244140625}, "domain": "pixel"}, {"position": {"minX": 442.0, "minY": -2.3125, "maxX": 680.0, "maxY": 161.0}, "class_id": 1, "box_caption": "rifle 0.002", "scores": {"class_score": 0.00249481201171875}, "domain": "pixel"}, {"position": {"minX": 5.375, "minY": 260.75, "maxX": 153.25, "maxY": 414.25}, "class_id": 0, "box_caption": "gun 0.002", "scores": {"class_score": 0.0024700164794921875}, "domain": "pixel"}, {"position": {"minX": 299.0, "minY": 1.25, "maxX": 629.5, "maxY": 159.0}, "class_id": 2, "box_caption": "knife 0.002", "scores": {"class_score": 0.002468109130859375}, "domain": "pixel"}, {"position": {"minX": -5.625, "minY": -2.375, "maxX": 354.5, "maxY": 163.375}, "class_id": 1, "box_caption": "rifle 0.002", "scores": {"class_score": 0.0024509429931640625}, "domain": "pixel"}, {"position": {"minX": 7.125, "minY": 2.125, "maxX": 279.0, "maxY": 283.5}, "class_id": 1, "box_caption": "rifle 0.002", "scores": {"class_score": 0.0024394989013671875}, "domain": "pixel"}, {"position": {"minX": 446.0, "minY": 256.75, "maxX": 674.0, "maxY": 423.25}, "class_id": 2, "box_caption": "knife 0.002", "scores": {"class_score": 0.002422332763671875}, "domain": "pixel"}, {"position": {"minX": 251.5, "minY": 1.8125, "maxX": 479.5, "maxY": 156.0}, "class_id": 1, "box_caption": "rifle 0.002", "scores": {"class_score": 0.0024013519287109375}, "domain": "pixel"}, {"position": {"minX": 226.125, "minY": 200.625, "maxX": 637.5, "maxY": 413.5}, "class_id": 2, "box_caption": "knife 0.002", "scores": {"class_score": 0.002391815185546875}, "domain": "pixel"}, {"position": {"minX": 32.5, "minY": 8.625, "maxX": 384.75, "maxY": 344.5}, "class_id": 2, "box_caption": "knife 0.002", "scores": {"class_score": 0.0023670196533203125}, "domain": "pixel"}, {"position": {"minX": 200.5, "minY": 30.0, "maxX": 537.0, "maxY": 320.5}, "class_id": 2, "box_caption": "knife 0.002", "scores": {"class_score": 0.0023632049560546875}, "domain": "pixel"}, {"position": {"minX": 2.3125, "minY": 1.375, "maxX": 162.25, "maxY": 221.0}, "class_id": 1, "box_caption": "rifle 0.002", "scores": {"class_score": 0.0023441314697265625}, "domain": "pixel"}, {"position": {"minX": 80.375, "minY": 69.875, "maxX": 591.0, "maxY": 412.5}, "class_id": 2, "box_caption": "knife 0.002", "scores": {"class_score": 0.00234222412109375}, "domain": "pixel"}, {"position": {"minX": 376.5, "minY": 334.25, "maxX": 680.5, "maxY": 413.75}, "class_id": 2, "box_caption": "knife 0.002", "scores": {"class_score": 0.0023345947265625}, "domain": "pixel"}, {"position": {"minX": 83.3125, "minY": 104.625, "maxX": 329.75, "maxY": 380.0}, "class_id": 2, "box_caption": "knife 0.002", "scores": {"class_score": 0.002315521240234375}, "domain": "pixel"}, {"position": {"minX": 70.25, "minY": 73.375, "maxX": 535.0, "maxY": 410.5}, "class_id": 0, "box_caption": "gun 0.002", "scores": {"class_score": 0.0023097991943359375}, "domain": "pixel"}, {"position": {"minX": 4.0625, "minY": -1.4375, "maxX": 214.75, "maxY": 222.75}, "class_id": 0, "box_caption": "gun 0.002", "scores": {"class_score": 0.002292633056640625}, "domain": "pixel"}, {"position": {"minX": 16.25, "minY": 1.375, "maxX": 467.0, "maxY": 284.0}, "class_id": 1, "box_caption": "rifle 0.002", "scores": {"class_score": 0.0022678375244140625}, "domain": "pixel"}, {"position": {"minX": -3.4375, "minY": 0.75, "maxX": 218.5, "maxY": 96.75}, "class_id": 2, "box_caption": "knife 0.002", "scores": {"class_score": 0.0022602081298828125}, "domain": "pixel"}, {"position": {"minX": 0.15625, "minY": 201.25, "maxX": 100.375, "maxY": 407.75}, "class_id": 2, "box_caption": "knife 0.002", "scores": {"class_score": 0.0022487640380859375}, "domain": "pixel"}, {"position": {"minX": -3.21875, "minY": 3.9375, "maxX": 107.5, "maxY": 216.75}, "class_id": 2, "box_caption": "knife 0.002", "scores": {"class_score": 0.002246856689453125}, "domain": "pixel"}, {"position": {"minX": 2.125, "minY": -4.0, "maxX": 158.625, "maxY": 161.0}, "class_id": 0, "box_caption": "gun 0.002", "scores": {"class_score": 0.0022411346435546875}, "domain": "pixel"}, {"position": {"minX": 116.0, "minY": 14.125, "maxX": 558.0, "maxY": 335.5}, "class_id": 1, "box_caption": "rifle 0.002", "scores": {"class_score": 0.00222015380859375}, "domain": "pixel"}, {"position": {"minX": 40.625, "minY": 333.0, "maxX": 434.5, "maxY": 412.0}, "class_id": 2, "box_caption": "knife 0.002", "scores": {"class_score": 0.002216339111328125}, "domain": "pixel"}, {"position": {"minX": 16.25, "minY": 1.375, "maxX": 467.0, "maxY": 284.0}, "class_id": 0, "box_caption": "gun 0.002", "scores": {"class_score": 0.002208709716796875}, "domain": "pixel"}, {"position": {"minX": -2.25, "minY": 323.75, "maxX": 162.5, "maxY": 413.75}, "class_id": 2, "box_caption": "knife 0.002", "scores": {"class_score": 0.00218963623046875}, "domain": "pixel"}, {"position": {"minX": 442.0, "minY": -2.3125, "maxX": 680.0, "maxY": 161.0}, "class_id": 0, "box_caption": "gun 0.002", "scores": {"class_score": 0.002178192138671875}, "domain": "pixel"}, {"position": {"minX": 1.0625, "minY": 154.25, "maxX": 158.75, "maxY": 393.25}, "class_id": 2, "box_caption": "knife 0.002", "scores": {"class_score": 0.0021762847900390625}, "domain": "pixel"}, {"position": {"minX": -2.25, "minY": 323.75, "maxX": 162.5, "maxY": 413.75}, "class_id": 0, "box_caption": "gun 0.002", "scores": {"class_score": 0.002147674560546875}, "domain": "pixel"}, {"position": {"minX": 224.0, "minY": 2.75, "maxX": 441.0, "maxY": 97.0}, "class_id": 2, "box_caption": "knife 0.002", "scores": {"class_score": 0.0021228790283203125}, "domain": "pixel"}, {"position": {"minX": 70.25, "minY": 73.375, "maxX": 535.0, "maxY": 410.5}, "class_id": 1, "box_caption": "rifle 0.002", "scores": {"class_score": 0.0021038055419921875}, "domain": "pixel"}, {"position": {"minX": 46.75, "minY": 197.25, "maxX": 494.25, "maxY": 413.25}, "class_id": 0, "box_caption": "gun 0.002", "scores": {"class_score": 0.0021038055419921875}, "domain": "pixel"}, {"position": {"minX": 47.5, "minY": 253.75, "maxX": 494.0, "maxY": 419.25}, "class_id": 1, "box_caption": "rifle 0.002", "scores": {"class_score": 0.00209808349609375}, "domain": "pixel"}, {"position": {"minX": 40.625, "minY": 333.0, "maxX": 434.5, "maxY": 412.0}, "class_id": 0, "box_caption": "gun 0.002", "scores": {"class_score": 0.002056121826171875}, "domain": "pixel"}, {"position": {"minX": 486.5, "minY": -6.9375, "maxX": 693.5, "maxY": 229.25}, "class_id": 1, "box_caption": "rifle 0.002", "scores": {"class_score": 0.0020542144775390625}, "domain": "pixel"}, {"position": {"minX": 337.75, "minY": 265.5, "maxX": 653.0, "maxY": 416.0}, "class_id": 2, "box_caption": "knife 0.002", "scores": {"class_score": 0.0020389556884765625}, "domain": "pixel"}, {"position": {"minX": 376.5, "minY": 334.25, "maxX": 680.5, "maxY": 413.75}, "class_id": 1, "box_caption": "rifle 0.002", "scores": {"class_score": 0.00203704833984375}, "domain": "pixel"}, {"position": {"minX": -4.5, "minY": -2.5, "maxX": 288.0, "maxY": 162.75}, "class_id": 0, "box_caption": "gun 0.002", "scores": {"class_score": 0.0020351409912109375}, "domain": "pixel"}, {"position": {"minX": 116.0, "minY": 14.125, "maxX": 558.0, "maxY": 335.5}, "class_id": 0, "box_caption": "gun 0.002", "scores": {"class_score": 0.00202178955078125}, "domain": "pixel"}, {"position": {"minX": 200.375, "minY": 270.25, "maxX": 598.5, "maxY": 412.75}, "class_id": 2, "box_caption": "knife 0.002", "scores": {"class_score": 0.001995086669921875}, "domain": "pixel"}, {"position": {"minX": 556.0, "minY": 69.0, "maxX": 683.0, "maxY": 413.0}, "class_id": 2, "box_caption": "knife 0.002", "scores": {"class_score": 0.00197601318359375}, "domain": "pixel"}, {"position": {"minX": 214.125, "minY": -1.78125, "maxX": 455.5, "maxY": 107.75}, "class_id": 1, "box_caption": "rifle 0.002", "scores": {"class_score": 0.0019702911376953125}, "domain": "pixel"}, {"position": {"minX": 38.5, "minY": 3.75, "maxX": 375.75, "maxY": 96.9375}, "class_id": 2, "box_caption": "knife 0.002", "scores": {"class_score": 0.0019550323486328125}, "domain": "pixel"}, {"position": {"minX": 486.5, "minY": -6.9375, "maxX": 693.5, "maxY": 229.25}, "class_id": 0, "box_caption": "gun 0.002", "scores": {"class_score": 0.0019550323486328125}, "domain": "pixel"}, {"position": {"minX": 388.0, "minY": 1.0625, "maxX": 666.0, "maxY": 100.375}, "class_id": 2, "box_caption": "knife 0.002", "scores": {"class_score": 0.0019197463989257812}, "domain": "pixel"}, {"position": {"minX": 58.375, "minY": 336.75, "maxX": 482.0, "maxY": 411.25}, "class_id": 1, "box_caption": "rifle 0.002", "scores": {"class_score": 0.0019140243530273438}, "domain": "pixel"}, {"position": {"minX": 228.625, "minY": 6.125, "maxX": 568.5, "maxY": 217.125}, "class_id": 1, "box_caption": "rifle 0.002", "scores": {"class_score": 0.001911163330078125}, "domain": "pixel"}, {"position": {"minX": 2.75, "minY": 261.0, "maxX": 97.5, "maxY": 412.5}, "class_id": 1, "box_caption": "rifle 0.002", "scores": {"class_score": 0.00189971923828125}, "domain": "pixel"}, {"position": {"minX": 136.375, "minY": 207.25, "maxX": 534.5, "maxY": 411.25}, "class_id": 2, "box_caption": "knife 0.002", "scores": {"class_score": 0.001880645751953125}, "domain": "pixel"}, {"position": {"minX": 251.5, "minY": 1.8125, "maxX": 479.5, "maxY": 156.0}, "class_id": 0, "box_caption": "gun 0.002", "scores": {"class_score": 0.0018777847290039062}, "domain": "pixel"}, {"position": {"minX": 499.5, "minY": -0.5625, "maxX": 677.5, "maxY": 99.75}, "class_id": 2, "box_caption": "knife 0.002", "scores": {"class_score": 0.001873016357421875}, "domain": "pixel"}, {"position": {"minX": 271.5, "minY": -0.75, "maxX": 718.0, "maxY": 351.0}, "class_id": 0, "box_caption": "gun 0.002", "scores": {"class_score": 0.0018558502197265625}, "domain": "pixel"}, {"position": {"minX": -4.5, "minY": -3.25, "maxX": 166.875, "maxY": 107.375}, "class_id": 1, "box_caption": "rifle 0.002", "scores": {"class_score": 0.0018367767333984375}, "domain": "pixel"}, {"position": {"minX": 221.125, "minY": 340.75, "maxX": 643.0, "maxY": 410.25}, "class_id": 2, "box_caption": "knife 0.002", "scores": {"class_score": 0.0018177032470703125}, "domain": "pixel"}, {"position": {"minX": 556.0, "minY": -5.375, "maxX": 682.0, "maxY": 162.5}, "class_id": 2, "box_caption": "knife 0.002", "scores": {"class_score": 0.0018148422241210938}, "domain": "pixel"}, {"position": {"minX": 0.625, "minY": 19.25, "maxX": 159.375, "maxY": 329.25}, "class_id": 2, "box_caption": "knife 0.002", "scores": {"class_score": 0.0017957687377929688}, "domain": "pixel"}, {"position": {"minX": 543.0, "minY": -6.75, "maxX": 697.0, "maxY": 292.0}, "class_id": 2, "box_caption": "knife 0.002", "scores": {"class_score": 0.0017919540405273438}, "domain": "pixel"}, {"position": {"minX": -3.8125, "minY": 140.875, "maxX": 166.25, "maxY": 406.5}, "class_id": 1, "box_caption": "rifle 0.002", "scores": {"class_score": 0.0017528533935546875}, "domain": "pixel"}, {"position": {"minX": 483.75, "minY": 331.25, "maxX": 691.5, "maxY": 416.25}, "class_id": 2, "box_caption": "knife 0.002", "scores": {"class_score": 0.00174713134765625}, "domain": "pixel"}, {"position": {"minX": -15.125, "minY": -0.5625, "maxX": 301.5, "maxY": 106.125}, "class_id": 1, "box_caption": "rifle 0.002", "scores": {"class_score": 0.0017414093017578125}, "domain": "pixel"}, {"position": {"minX": 446.0, "minY": 256.75, "maxX": 674.0, "maxY": 423.25}, "class_id": 1, "box_caption": "rifle 0.002", "scores": {"class_score": 0.0017328262329101562}, "domain": "pixel"}, {"position": {"minX": 41.25, "minY": 250.875, "maxX": 567.0, "maxY": 422.0}, "class_id": 2, "box_caption": "knife 0.002", "scores": {"class_score": 0.0017156600952148438}, "domain": "pixel"}, {"position": {"minX": 348.0, "minY": 1.25, "maxX": 644.5, "maxY": 157.875}, "class_id": 1, "box_caption": "rifle 0.002", "scores": {"class_score": 0.0017147064208984375}, "domain": "pixel"}, {"position": {"minX": 520.5, "minY": -35.0, "maxX": 718.5, "maxY": 388.5}, "class_id": 2, "box_caption": "knife 0.002", "scores": {"class_score": 0.001697540283203125}, "domain": "pixel"}, {"position": {"minX": 296.0, "minY": 313.0, "maxX": 698.5, "maxY": 418.5}, "class_id": 1, "box_caption": "rifle 0.002", "scores": {"class_score": 0.0016803741455078125}, "domain": "pixel"}, {"position": {"minX": -4.625, "minY": 71.75, "maxX": 228.875, "maxY": 413.25}, "class_id": 1, "box_caption": "rifle 0.002", "scores": {"class_score": 0.00167083740234375}, "domain": "pixel"}, {"position": {"minX": -3.625, "minY": 4.3125, "maxX": 106.25, "maxY": 156.0}, "class_id": 1, "box_caption": "rifle 0.002", "scores": {"class_score": 0.0016679763793945312}, "domain": "pixel"}, {"position": {"minX": 271.0, "minY": 3.96875, "maxX": 588.0, "maxY": 96.625}, "class_id": 2, "box_caption": "knife 0.002", "scores": {"class_score": 0.0016641616821289062}, "domain": "pixel"}, {"position": {"minX": 49.875, "minY": -3.78125, "maxX": 432.0, "maxY": 108.875}, "class_id": 1, "box_caption": "rifle 0.002", "scores": {"class_score": 0.0016603469848632812}, "domain": "pixel"}, {"position": {"minX": 271.5, "minY": -0.75, "maxX": 718.0, "maxY": 351.0}, "class_id": 1, "box_caption": "rifle 0.002", "scores": {"class_score": 0.00165557861328125}, "domain": "pixel"}, {"position": {"minX": 376.5, "minY": 334.25, "maxX": 680.5, "maxY": 413.75}, "class_id": 0, "box_caption": "gun 0.002", "scores": {"class_score": 0.0016489028930664062}, "domain": "pixel"}, {"position": {"minX": 295.25, "minY": 0.5625, "maxX": 698.0, "maxY": 223.5}, "class_id": 1, "box_caption": "rifle 0.002", "scores": {"class_score": 0.0016374588012695312}, "domain": "pixel"}, {"position": {"minX": 141.5, "minY": 189.25, "maxX": 660.0, "maxY": 421.25}, "class_id": 1, "box_caption": "rifle 0.002", "scores": {"class_score": 0.0016355514526367188}, "domain": "pixel"}, {"position": {"minX": 504.25, "minY": 125.75, "maxX": 677.0, "maxY": 420.75}, "class_id": 0, "box_caption": "gun 0.002", "scores": {"class_score": 0.00160980224609375}, "domain": "pixel"}, {"position": {"minX": 208.5, "minY": 55.25, "maxX": 531.0, "maxY": 367.75}, "class_id": 1, "box_caption": "rifle 0.002", "scores": {"class_score": 0.0016078948974609375}, "domain": "pixel"}, {"position": {"minX": -4.625, "minY": 71.75, "maxX": 228.875, "maxY": 413.25}, "class_id": 0, "box_caption": "gun 0.002", "scores": {"class_score": 0.0016050338745117188}, "domain": "pixel"}, {"position": {"minX": 122.0, "minY": -3.15625, "maxX": 422.0, "maxY": 108.0}, "class_id": 2, "box_caption": "knife 0.002", "scores": {"class_score": 0.0016040802001953125}, "domain": "pixel"}, {"position": {"minX": 12.375, "minY": 361.75, "maxX": 273.0, "maxY": 420.25}, "class_id": 1, "box_caption": "rifle 0.002", "scores": {"class_score": 0.0016012191772460938}, "domain": "pixel"}, {"position": {"minX": 504.25, "minY": 177.0, "maxX": 676.0, "maxY": 435.5}, "class_id": 1, "box_caption": "rifle 0.002", "scores": {"class_score": 0.0015974044799804688}, "domain": "pixel"}, {"position": {"minX": 446.0, "minY": 256.75, "maxX": 674.0, "maxY": 423.25}, "class_id": 0, "box_caption": "gun 0.002", "scores": {"class_score": 0.0015811920166015625}, "domain": "pixel"}, {"position": {"minX": 493.75, "minY": -5.125, "maxX": 688.5, "maxY": 111.5}, "class_id": 1, "box_caption": "rifle 0.002", "scores": {"class_score": 0.00157928466796875}, "domain": "pixel"}, {"position": {"minX": 221.125, "minY": 340.75, "maxX": 643.0, "maxY": 410.25}, "class_id": 1, "box_caption": "rifle 0.002", "scores": {"class_score": 0.0015773773193359375}, "domain": "pixel"}, {"position": {"minX": 296.0, "minY": 313.0, "maxX": 698.5, "maxY": 418.5}, "class_id": 2, "box_caption": "knife 0.002", "scores": {"class_score": 0.0015707015991210938}, "domain": "pixel"}, {"position": {"minX": 483.75, "minY": 331.25, "maxX": 691.5, "maxY": 416.25}, "class_id": 1, "box_caption": "rifle 0.002", "scores": {"class_score": 0.00152587890625}, "domain": "pixel"}, {"position": {"minX": 318.25, "minY": 139.25, "maxX": 673.0, "maxY": 407.75}, "class_id": 1, "box_caption": "rifle 0.002", "scores": {"class_score": 0.0015249252319335938}, "domain": "pixel"}, {"position": {"minX": 318.25, "minY": 139.25, "maxX": 673.0, "maxY": 407.75}, "class_id": 0, "box_caption": "gun 0.002", "scores": {"class_score": 0.0015172958374023438}, "domain": "pixel"}, {"position": {"minX": -4.46875, "minY": 97.375, "maxX": 103.75, "maxY": 388.0}, "class_id": 2, "box_caption": "knife 0.002", "scores": {"class_score": 0.0015163421630859375}, "domain": "pixel"}, {"position": {"minX": 152.375, "minY": 3.46875, "maxX": 388.5, "maxY": 94.875}, "class_id": 1, "box_caption": "rifle 0.002", "scores": {"class_score": 0.0015115737915039062}, "domain": "pixel"}, {"position": {"minX": 0.15625, "minY": 201.25, "maxX": 100.375, "maxY": 407.75}, "class_id": 0, "box_caption": "gun 0.002", "scores": {"class_score": 0.0015096664428710938}, "domain": "pixel"}, {"position": {"minX": 300.0, "minY": -7.8125, "maxX": 691.0, "maxY": 114.25}, "class_id": 2, "box_caption": "knife 0.002", "scores": {"class_score": 0.0015039443969726562}, "domain": "pixel"}, {"position": {"minX": 26.5, "minY": 308.5, "maxX": 582.5, "maxY": 421.5}, "class_id": 1, "box_caption": "rifle 0.002", "scores": {"class_score": 0.0015039443969726562}, "domain": "pixel"}, {"position": {"minX": 168.75, "minY": 145.75, "maxX": 571.0, "maxY": 406.25}, "class_id": 0, "box_caption": "gun 0.002", "scores": {"class_score": 0.00150299072265625}, "domain": "pixel"}, {"position": {"minX": 31.0, "minY": 310.5, "maxX": 513.0, "maxY": 418.5}, "class_id": 2, "box_caption": "knife 0.001", "scores": {"class_score": 0.0014963150024414062}, "domain": "pixel"}, {"position": {"minX": 328.0, "minY": 0.375, "maxX": 665.0, "maxY": 222.75}, "class_id": 0, "box_caption": "gun 0.001", "scores": {"class_score": 0.0014867782592773438}, "domain": "pixel"}, {"position": {"minX": -8.375, "minY": 1.65625, "maxX": 106.5, "maxY": 94.25}, "class_id": 2, "box_caption": "knife 0.001", "scores": {"class_score": 0.0014743804931640625}, "domain": "pixel"}, {"position": {"minX": 233.0, "minY": 268.25, "maxX": 630.0, "maxY": 413.75}, "class_id": 1, "box_caption": "rifle 0.001", "scores": {"class_score": 0.00147247314453125}, "domain": "pixel"}, {"position": {"minX": -3.8125, "minY": 140.875, "maxX": 166.25, "maxY": 406.5}, "class_id": 0, "box_caption": "gun 0.001", "scores": {"class_score": 0.0014715194702148438}, "domain": "pixel"}, {"position": {"minX": 363.0, "minY": -6.75, "maxX": 694.0, "maxY": 112.75}, "class_id": 1, "box_caption": "rifle 0.001", "scores": {"class_score": 0.00145721435546875}, "domain": "pixel"}, {"position": {"minX": 547.5, "minY": 38.875, "maxX": 689.5, "maxY": 444.0}, "class_id": 0, "box_caption": "gun 0.001", "scores": {"class_score": 0.0014390945434570312}, "domain": "pixel"}, {"position": {"minX": 12.375, "minY": 361.75, "maxX": 273.0, "maxY": 420.25}, "class_id": 2, "box_caption": "knife 0.001", "scores": {"class_score": 0.0014190673828125}, "domain": "pixel"}, {"position": {"minX": 432.5, "minY": 364.5, "maxX": 685.5, "maxY": 421.0}, "class_id": 2, "box_caption": "knife 0.001", "scores": {"class_score": 0.0014162063598632812}, "domain": "pixel"}, {"position": {"minX": -2.03125, "minY": 155.875, "maxX": 101.0, "maxY": 393.0}, "class_id": 1, "box_caption": "rifle 0.001", "scores": {"class_score": 0.0014162063598632812}, "domain": "pixel"}, {"position": {"minX": -4.75, "minY": -6.5, "maxX": 166.25, "maxY": 356.75}, "class_id": 1, "box_caption": "rifle 0.001", "scores": {"class_score": 0.001399993896484375}, "domain": "pixel"}, {"position": {"minX": -4.75, "minY": -6.5, "maxX": 166.25, "maxY": 356.75}, "class_id": 0, "box_caption": "gun 0.001", "scores": {"class_score": 0.00139617919921875}, "domain": "pixel"}, {"position": {"minX": 547.5, "minY": 38.875, "maxX": 689.5, "maxY": 444.0}, "class_id": 1, "box_caption": "rifle 0.001", "scores": {"class_score": 0.001392364501953125}, "domain": "pixel"}, {"position": {"minX": 226.125, "minY": 200.625, "maxX": 637.5, "maxY": 413.5}, "class_id": 0, "box_caption": "gun 0.001", "scores": {"class_score": 0.0013875961303710938}, "domain": "pixel"}, {"position": {"minX": -2.25, "minY": 311.75, "maxX": 105.375, "maxY": 415.25}, "class_id": 1, "box_caption": "rifle 0.001", "scores": {"class_score": 0.0013761520385742188}, "domain": "pixel"}, {"position": {"minX": 562.0, "minY": 183.25, "maxX": 675.0, "maxY": 427.25}, "class_id": 2, "box_caption": "knife 0.001", "scores": {"class_score": 0.0013742446899414062}, "domain": "pixel"}, {"position": {"minX": -3.21875, "minY": 3.9375, "maxX": 107.5, "maxY": 216.75}, "class_id": 0, "box_caption": "gun 0.001", "scores": {"class_score": 0.0013647079467773438}, "domain": "pixel"}, {"position": {"minX": 133.375, "minY": 343.5, "maxX": 537.0, "maxY": 410.5}, "class_id": 2, "box_caption": "knife 0.001", "scores": {"class_score": 0.0013589859008789062}, "domain": "pixel"}, {"position": {"minX": -6.0625, "minY": 10.125, "maxX": 107.4375, "maxY": 277.5}, "class_id": 1, "box_caption": "rifle 0.001", "scores": {"class_score": 0.0013523101806640625}, "domain": "pixel"}, {"position": {"minX": 520.5, "minY": -35.0, "maxX": 718.5, "maxY": 388.5}, "class_id": 0, "box_caption": "gun 0.001", "scores": {"class_score": 0.00135040283203125}, "domain": "pixel"}, {"position": {"minX": 31.0, "minY": 310.5, "maxX": 513.0, "maxY": 418.5}, "class_id": 0, "box_caption": "gun 0.001", "scores": {"class_score": 0.00135040283203125}, "domain": "pixel"}, {"position": {"minX": -3.4375, "minY": 0.75, "maxX": 218.5, "maxY": 96.75}, "class_id": 0, "box_caption": "gun 0.001", "scores": {"class_score": 0.0013380050659179688}, "domain": "pixel"}, {"position": {"minX": 547.0, "minY": -11.8125, "maxX": 691.0, "maxY": 171.5}, "class_id": 1, "box_caption": "rifle 0.001", "scores": {"class_score": 0.001331329345703125}, "domain": "pixel"}, {"position": {"minX": -2.25, "minY": 311.75, "maxX": 105.375, "maxY": 415.25}, "class_id": 2, "box_caption": "knife 0.001", "scores": {"class_score": 0.0013275146484375}, "domain": "pixel"}, {"position": {"minX": 208.5, "minY": 55.25, "maxX": 531.0, "maxY": 367.75}, "class_id": 0, "box_caption": "gun 0.001", "scores": {"class_score": 0.0013265609741210938}, "domain": "pixel"}, {"position": {"minX": 217.75, "minY": -8.625, "maxX": 645.0, "maxY": 114.1875}, "class_id": 1, "box_caption": "rifle 0.001", "scores": {"class_score": 0.001316070556640625}, "domain": "pixel"}, {"position": {"minX": 299.0, "minY": 1.25, "maxX": 629.5, "maxY": 159.0}, "class_id": 0, "box_caption": "gun 0.001", "scores": {"class_score": 0.001312255859375}, "domain": "pixel"}, {"position": {"minX": 8.25, "minY": 323.75, "maxX": 279.25, "maxY": 413.75}, "class_id": 3, "box_caption": "baseball 0.001", "scores": {"class_score": 0.0013093948364257812}, "domain": "pixel"}, {"position": {"minX": 224.0, "minY": 2.75, "maxX": 441.0, "maxY": 97.0}, "class_id": 0, "box_caption": "gun 0.001", "scores": {"class_score": 0.0012922286987304688}, "domain": "pixel"}, {"position": {"minX": 79.375, "minY": 48.875, "maxX": 400.5, "maxY": 372.0}, "class_id": 1, "box_caption": "rifle 0.001", "scores": {"class_score": 0.0012760162353515625}, "domain": "pixel"}, {"position": {"minX": 344.5, "minY": 368.0, "maxX": 646.5, "maxY": 419.5}, "class_id": 2, "box_caption": "knife 0.001", "scores": {"class_score": 0.0012645721435546875}, "domain": "pixel"}, {"position": {"minX": 296.0, "minY": 313.0, "maxX": 698.5, "maxY": 418.5}, "class_id": 0, "box_caption": "gun 0.001", "scores": {"class_score": 0.0012502670288085938}, "domain": "pixel"}, {"position": {"minX": 520.5, "minY": -35.0, "maxX": 718.5, "maxY": 388.5}, "class_id": 1, "box_caption": "rifle 0.001", "scores": {"class_score": 0.0012493133544921875}, "domain": "pixel"}, {"position": {"minX": 221.125, "minY": 340.75, "maxX": 643.0, "maxY": 410.25}, "class_id": 0, "box_caption": "gun 0.001", "scores": {"class_score": 0.001239776611328125}, "domain": "pixel"}, {"position": {"minX": 15.125, "minY": 259.0, "maxX": 271.0, "maxY": 415.5}, "class_id": 3, "box_caption": "baseball 0.001", "scores": {"class_score": 0.00118255615234375}, "domain": "pixel"}, {"position": {"minX": 483.75, "minY": 331.25, "maxX": 691.5, "maxY": 416.25}, "class_id": 0, "box_caption": "gun 0.001", "scores": {"class_score": 0.0011749267578125}, "domain": "pixel"}, {"position": {"minX": 263.5, "minY": 4.1875, "maxX": 530.0, "maxY": 95.3125}, "class_id": 1, "box_caption": "rifle 0.001", "scores": {"class_score": 0.0011491775512695312}, "domain": "pixel"}, {"position": {"minX": 80.0, "minY": 246.0, "maxX": 658.0, "maxY": 426.5}, "class_id": 0, "box_caption": "gun 0.001", "scores": {"class_score": 0.0011386871337890625}, "domain": "pixel"}, {"position": {"minX": 200.375, "minY": 270.25, "maxX": 598.5, "maxY": 412.75}, "class_id": 0, "box_caption": "gun 0.001", "scores": {"class_score": 0.001132965087890625}, "domain": "pixel"}, {"position": {"minX": 432.5, "minY": 364.5, "maxX": 685.5, "maxY": 421.0}, "class_id": 1, "box_caption": "rifle 0.001", "scores": {"class_score": 0.0011157989501953125}, "domain": "pixel"}, {"position": {"minX": 152.375, "minY": 3.46875, "maxX": 388.5, "maxY": 94.875}, "class_id": 0, "box_caption": "gun 0.001", "scores": {"class_score": 0.0011053085327148438}, "domain": "pixel"}, {"position": {"minX": -15.1875, "minY": 363.25, "maxX": 173.5, "maxY": 417.25}, "class_id": 2, "box_caption": "knife 0.001", "scores": {"class_score": 0.00109100341796875}, "domain": "pixel"}, {"position": {"minX": 540.5, "minY": -13.59375, "maxX": 698.5, "maxY": 119.125}, "class_id": 2, "box_caption": "knife 0.001", "scores": {"class_score": 0.0010814666748046875}, "domain": "pixel"}, {"position": {"minX": -2.25, "minY": 323.75, "maxX": 162.5, "maxY": 413.75}, "class_id": 3, "box_caption": "baseball 0.001", "scores": {"class_score": 0.0010805130004882812}, "domain": "pixel"}, {"position": {"minX": 49.875, "minY": -3.78125, "maxX": 432.0, "maxY": 108.875}, "class_id": 0, "box_caption": "gun 0.001", "scores": {"class_score": 0.0010786056518554688}, "domain": "pixel"}, {"position": {"minX": 313.25, "minY": 250.125, "maxX": 680.0, "maxY": 423.5}, "class_id": 0, "box_caption": "gun 0.001", "scores": {"class_score": 0.00106048583984375}, "domain": "pixel"}, {"position": {"minX": 556.0, "minY": -5.375, "maxX": 682.0, "maxY": 162.5}, "class_id": 0, "box_caption": "gun 0.001", "scores": {"class_score": 0.0010585784912109375}, "domain": "pixel"}, {"position": {"minX": 499.5, "minY": -0.5625, "maxX": 677.5, "maxY": 99.75}, "class_id": 0, "box_caption": "gun 0.001", "scores": {"class_score": 0.0010576248168945312}, "domain": "pixel"}, {"position": {"minX": 12.375, "minY": 361.75, "maxX": 273.0, "maxY": 420.25}, "class_id": 0, "box_caption": "gun 0.001", "scores": {"class_score": 0.0010557174682617188}, "domain": "pixel"}, {"position": {"minX": 543.0, "minY": -6.75, "maxX": 697.0, "maxY": 292.0}, "class_id": 1, "box_caption": "rifle 0.001", "scores": {"class_score": 0.0010461807250976562}, "domain": "pixel"}, {"position": {"minX": 38.625, "minY": 195.0, "maxX": 309.0, "maxY": 414.0}, "class_id": 3, "box_caption": "baseball 0.001", "scores": {"class_score": 0.0010461807250976562}, "domain": "pixel"}, {"position": {"minX": 73.375, "minY": 366.25, "maxX": 336.0, "maxY": 419.75}, "class_id": 1, "box_caption": "rifle 0.001", "scores": {"class_score": 0.0010423660278320312}, "domain": "pixel"}, {"position": {"minX": 554.0, "minY": 231.625, "maxX": 683.0, "maxY": 443.5}, "class_id": 1, "box_caption": "rifle 0.001", "scores": {"class_score": 0.001033782958984375}, "domain": "pixel"}, {"position": {"minX": 73.375, "minY": 366.25, "maxX": 336.0, "maxY": 419.75}, "class_id": 2, "box_caption": "knife 0.001", "scores": {"class_score": 0.001026153564453125}, "domain": "pixel"}, {"position": {"minX": -8.375, "minY": 1.65625, "maxX": 106.5, "maxY": 94.25}, "class_id": 1, "box_caption": "rifle 0.001", "scores": {"class_score": 0.0010194778442382812}, "domain": "pixel"}, {"position": {"minX": -15.1875, "minY": 363.25, "maxX": 173.5, "maxY": 417.25}, "class_id": 1, "box_caption": "rifle 0.001", "scores": {"class_score": 0.0010175704956054688}, "domain": "pixel"}, {"position": {"minX": -4.46875, "minY": 97.375, "maxX": 103.75, "maxY": 388.0}, "class_id": 0, "box_caption": "gun 0.001", "scores": {"class_score": 0.0010099411010742188}, "domain": "pixel"}, {"position": {"minX": 543.0, "minY": -6.75, "maxX": 697.0, "maxY": 292.0}, "class_id": 0, "box_caption": "gun 0.001", "scores": {"class_score": 0.001003265380859375}, "domain": "pixel"}], "class_labels": {"0": "gun", "1": "rifle", "2": "knife", "3": "baseball"}}